nlpstack/__init__.py
nlpstack/__main__.py
nlpstack/commands/__init__.py
nlpstack/commands/subcommand.py
nlpstack/commands/workflow.py
nlpstack/common/__init__.py
nlpstack/common/automaton.py
nlpstack/common/bleu.py
nlpstack/common/cacheutil.py
nlpstack/common/filebackend.py
nlpstack/common/hashutil.py
nlpstack/common/iterutil.py
nlpstack/common/jsonnet.py
nlpstack/common/jsonschema.py
nlpstack/common/pipeline.py
nlpstack/common/platform.py
nlpstack/common/progressbar.py
nlpstack/data/__init__.py
nlpstack/data/dataloaders.py
nlpstack/data/datamodule.py
nlpstack/data/embeddings.py
nlpstack/data/fields.py
nlpstack/data/generators.py
nlpstack/data/indexers.py
nlpstack/data/tokenizers.py
nlpstack/data/util.py
nlpstack/data/vocabulary.py
nlpstack/evaluation/__init__.py
nlpstack/evaluation/evaluators.py
nlpstack/evaluation/metrics.py
nlpstack/integrations/__init__.py
nlpstack/integrations/mlflow/__init__.py
nlpstack/integrations/mlflow/util.py
nlpstack/integrations/mlflow/workflow.py
nlpstack/integrations/optuna/__init__.py
nlpstack/integrations/optuna/config.py
nlpstack/integrations/sklearn/__init__.py
nlpstack/integrations/sklearn/rune.py
nlpstack/integrations/torch/__init__.py
nlpstack/integrations/torch/generation/__init__.py
nlpstack/integrations/torch/generation/beam_search.py
nlpstack/integrations/torch/generation/constraints.py
nlpstack/integrations/torch/generation/samplers.py
nlpstack/integrations/torch/generation/scorers.py
nlpstack/integrations/torch/model.py
nlpstack/integrations/torch/modules/__init__.py
nlpstack/integrations/torch/modules/count_embedder.py
nlpstack/integrations/torch/modules/crf.py
nlpstack/integrations/torch/modules/feedforward.py
nlpstack/integrations/torch/modules/heads.py
nlpstack/integrations/torch/modules/lazy.py
nlpstack/integrations/torch/modules/scalarmix.py
nlpstack/integrations/torch/modules/seq2seq_decoders.py
nlpstack/integrations/torch/modules/seq2seq_encoders.py
nlpstack/integrations/torch/modules/seq2vec_encoders.py
nlpstack-0.2.0.dist-info/LICENSE
nlpstack-0.2.0.dist-info/METADATA
nlpstack-0.2.0.dist-info/WHEEL
nlpstack-0.2.0.dist-info/entry_points.txt
nlpstack-0.2.0.dist-info/RECORD
