Metadata-Version: 2.1
Name: nlpstack
Version: 0.2.0
Summary: Modules for NLP
Home-page: https://github.com/altescy/nlpstack
License: MIT
Keywords: python,nlp,pytorch,scikit-learn
Author: altescy
Author-email: altescy@fastmail.com
Requires-Python: >=3.8,<4.0
Classifier: License :: OSI Approved :: MIT License
Classifier: Programming Language :: Python :: 3
Classifier: Programming Language :: Python :: 3.8
Classifier: Programming Language :: Python :: 3.9
Classifier: Programming Language :: Python :: 3.10
Classifier: Programming Language :: Python :: 3.11
Classifier: Programming Language :: Python :: 3.12
Provides-Extra: all
Requires-Dist: collatable (>=0.3.2)
Requires-Dist: colt (>=0.11.3)
Requires-Dist: dill
Requires-Dist: fasttext-wheel (>=0.9,<1.0) ; extra == "all"
Requires-Dist: fugashi[unidic-lite] (>=1.2.1,<2.0) ; extra == "all"
Requires-Dist: minato (>=0.12)
Requires-Dist: mlflow (>=2.0,<3.0) ; extra == "all"
Requires-Dist: mpire (>=2.0,<3.0)
Requires-Dist: numpy
Requires-Dist: openai (>=1.0,<2.0) ; extra == "all"
Requires-Dist: optuna (>=3.2,<4.0) ; extra == "all"
Requires-Dist: rjsonnet (>=0.5)
Requires-Dist: scikit-learn (>=1.0,<2.0)
Requires-Dist: sentence-transformers (>=2.2.2) ; extra == "all"
Requires-Dist: spacy (>=3.5.3,<4.0) ; extra == "all"
Requires-Dist: torch (>=1.9,<3.0)
Requires-Dist: transformers (>=4.12.3,<5.0) ; extra == "all"
